sort_requirements/__init__.py
sort_requirements/script.py
sort_requirements-1.3.0.dist-info/LICENSE
sort_requirements-1.3.0.dist-info/METADATA
sort_requirements-1.3.0.dist-info/WHEEL
sort_requirements-1.3.0.dist-info/entry_points.txt
sort_requirements-1.3.0.dist-info/top_level.txt
sort_requirements-1.3.0.dist-info/RECORD
