Metadata-Version: 1.1
Name: sort_requirements
Version: 1.3.0
Summary: A simple script to sort python dependencies in requirement text files.
Home-page: https://github.com/rehandalal/sort-requirements
Author: Rehan Dalal
Author-email: rehan@meet-rehan.com
License: Mozilla Public License Version 2.0
Platform: any
Classifier: Development Status :: 5 - Production/Stable
Classifier: Environment :: Console
Classifier: Intended Audience :: Developers
Classifier: License :: OSI Approved :: Mozilla Public License 2.0 (MPL 2.0)
Classifier: Natural Language :: English
Classifier: Operating System :: MacOS
Classifier: Operating System :: Unix
Classifier: Programming Language :: Python
Classifier: Programming Language :: Python :: 2.7
Classifier: Programming Language :: Python :: 3.4
Classifier: Programming Language :: Python :: 3.5
Classifier: Programming Language :: Python :: 3.6
Classifier: Programming Language :: Python :: 3.7
Classifier: Topic :: Software Development :: Build Tools
